README.md
douyin_downloader.py
douyin_tool.py
setup.py
util.py
douyin_downloader.egg-info/PKG-INFO
douyin_downloader.egg-info/SOURCES.txt
douyin_downloader.egg-info/dependency_links.txt
douyin_downloader.egg-info/entry_points.txt
douyin_downloader.egg-info/not-zip-safe
douyin_downloader.egg-info/requires.txt
douyin_downloader.egg-info/top_level.txt