Metadata-Version: 1.1
Name: douyin-downloader
Version: 1.0.1
Summary: The douyin video downloader
Home-page: https://github.com/HeLiangHIT/douyin_downloader
Author: He Liang
Author-email: heianghit@foxmail.com
License: GPLv3
Keywords: douyin trio
Platform: UNKNOWN
Classifier: Programming Language :: Python :: 3
Classifier: Development Status :: 3 - Alpha
Classifier: Natural Language :: English
Classifier: Environment :: Console
Classifier: Intended Audience :: Developers
Classifier: Operating System :: OS Independent
Classifier: Topic :: Utilities
Classifier: License :: OSI Approved :: GNU General Public License (GPL)
